{"cameraMode":{"drawMode":0,"name":"Shaded","section":"Shading Mode"},"sceneLighting":false,"audioPlay":false,"sceneViewState":{"m_AlwaysRefresh":false,"showFog":true,"showSkybox":false,"showFlares":true,"showImageEffects":true,"showParticleSystems":true,"showVisualEffectGraphs":true,"m_FxEnabled":true},"in2DMode":false,"pivot":{"x":24.647262573242189,"y":-7.407717704772949,"z":4.8623762130737309},"rotation":{"x":0.10886621475219727,"y":0.6529001593589783,"z":-0.09560398757457733,"w":0.7434608340263367},"size":16.78956413269043,"orthographic":false}